FERMI/AdultDataset.py
FERMI/FERMIBinary.py
FERMI/__init__.py
FERMI/test.py
FERMI_ODDS-0.0.1.dist-info/LICENSE
FERMI_ODDS-0.0.1.dist-info/METADATA
FERMI_ODDS-0.0.1.dist-info/WHEEL
FERMI_ODDS-0.0.1.dist-info/top_level.txt
FERMI_ODDS-0.0.1.dist-info/RECORD
