Metadata-Version: 2.1
Name: FERMI-ODDS
Version: 0.0.1
Summary: Fair Empirical Risk Minimization via Exponential Renyi Mutual Information (ERMI)
Author-email: Sina Baharlouei <baharlou@usc.edu>
Project-URL: Homepage, https://github.com/optimization-for-data-driven-science/FERMI
Project-URL: Bug Tracker, https://github.com/optimization-for-data-driven-science/FERMI
Classifier: Programming Language :: Python :: 3
Classifier: License :: OSI Approved :: MIT License
Classifier: Operating System :: OS Independent
Requires-Python: >=3.7
License-File: LICENSE
